wedata/__init__.py
wedata/api.py
wedata/checker.py
wedata/client.py
wedata/client_local.py
wedata/config.py
wedata/utils.py
wiserdata/__init__.py
wiserdata/api.py
wiserdata/checker.py
wiserdata/client.py
wiserdata/client_local.py
wiserdata/config.py
wiserdata/status_code.py
wiserdata/uploader.py
wiserdata/utils.py
wiserdata/tools/__init__.py
wiserdata/tools/exception.py
wiserdata/tools/status.py
wiserdata-0.0.15.dist-info/METADATA
wiserdata-0.0.15.dist-info/WHEEL
wiserdata-0.0.15.dist-info/top_level.txt
wiserdata-0.0.15.dist-info/RECORD
